src/topsis.py
TOPSIS_SuvidhaSrivastava_102103019-0.1.0.dist-info/METADATA
TOPSIS_SuvidhaSrivastava_102103019-0.1.0.dist-info/WHEEL
TOPSIS_SuvidhaSrivastava_102103019-0.1.0.dist-info/entry_points.txt
TOPSIS_SuvidhaSrivastava_102103019-0.1.0.dist-info/top_level.txt
TOPSIS_SuvidhaSrivastava_102103019-0.1.0.dist-info/RECORD
