Metadata-Version: 2.1
Name: TOPSIS-SuvidhaSrivastava-102103019
Version: 0.1.0
Summary: Python package for implementing TOPSIS technique.
Author: Suvidha Srivastava
Author-email: ssrivastava1_be21@thapar.edu
License: MIT
Classifier: License :: OSI Approved :: MIT License
Classifier: Programming Language :: Python :: 3
Classifier: Programming Language :: Python :: 3.4
Classifier: Programming Language :: Python :: 3.5
Classifier: Programming Language :: Python :: 3.6
Classifier: Programming Language :: Python :: 3.7
Requires-Dist: scipy
Requires-Dist: tabulate
Requires-Dist: numpy
Requires-Dist: pandas
